invenio_records_resources/__init__.py
invenio_records_resources/config.py
invenio_records_resources/errors.py
invenio_records_resources/ext.py
invenio_records_resources/pagination.py
invenio_records_resources/proxies.py
invenio_records_resources/registry.py
invenio_records_resources/tasks.py
invenio_records_resources/factories/__init__.py
invenio_records_resources/factories/factory.py
invenio_records_resources/records/__init__.py
invenio_records_resources/records/api.py
invenio_records_resources/records/dumpers.py
invenio_records_resources/records/models.py
invenio_records_resources/records/providers.py
invenio_records_resources/records/resolver.py
invenio_records_resources/records/transfer.py
invenio_records_resources/records/jsonschemas/__init__.py
invenio_records_resources/records/jsonschemas/definitions-v1.0.0.json
invenio_records_resources/records/jsonschemas/definitions-v2.0.0.json
invenio_records_resources/records/systemfields/__init__.py
invenio_records_resources/records/systemfields/calculated.py
invenio_records_resources/records/systemfields/entity_reference.py
invenio_records_resources/records/systemfields/index.py
invenio_records_resources/records/systemfields/pid.py
invenio_records_resources/records/systemfields/pid_statuscheck.py
invenio_records_resources/records/systemfields/relations.py
invenio_records_resources/records/systemfields/files/__init__.py
invenio_records_resources/records/systemfields/files/field.py
invenio_records_resources/records/systemfields/files/manager.py
invenio_records_resources/references/__init__.py
invenio_records_resources/references/grants.py
invenio_records_resources/references/registry.py
invenio_records_resources/references/entity_resolvers/__init__.py
invenio_records_resources/references/entity_resolvers/base.py
invenio_records_resources/references/entity_resolvers/records.py
invenio_records_resources/references/entity_resolvers/results.py
invenio_records_resources/resources/__init__.py
invenio_records_resources-9.0.0.dist-info/licenses/AUTHORS.rst
invenio_records_resources-9.0.0.dist-info/licenses/LICENSE
invenio_records_resources-9.0.0.dist-info/METADATA
invenio_records_resources-9.0.0.dist-info/WHEEL
invenio_records_resources-9.0.0.dist-info/entry_points.txt
invenio_records_resources-9.0.0.dist-info/top_level.txt
invenio_records_resources-9.0.0.dist-info/RECORD
