Metadata-Version: 2.4
Name: invenio-records-resources
Version: 9.0.0
Summary: Invenio resources module to create REST APIs.
Home-page: https://github.com/inveniosoftware/invenio-records-resources
Author: CERN
Author-email: info@inveniosoftware.org
License: MIT
Keywords: invenio records rest api_blueprints
Platform: any
Classifier: Development Status :: 5 - Production/Stable
Requires-Python: >=3.7
License-File: LICENSE
License-File: AUTHORS.rst
Requires-Dist: babel-edtf>=1.1.0
Requires-Dist: flask-resources<2.0.0,>=1.0.0
Requires-Dist: invenio-accounts<8.0.0,>=7.0.0
Requires-Dist: invenio-base<3.0.0,>=2.4.0
Requires-Dist: invenio-db<3.0.0,>=2.2.0
Requires-Dist: invenio-files-rest<5.0.0,>=4.0.0
Requires-Dist: invenio-i18n<4.0.0,>=3.0.0
Requires-Dist: invenio-indexer<5.0.0,>=4.0.0
Requires-Dist: invenio-jsonschemas<3.0.0,>=2.0.0
Requires-Dist: invenio-pidstore<4.0.0,>=3.0.0
Requires-Dist: invenio-records-permissions<3.0.0,>=2.0.0
Requires-Dist: invenio-records<5.0.0,>=4.0.0
Requires-Dist: invenio-stats<7.0.0,>=6.0.0
Requires-Dist: luqum>=0.11.0
Requires-Dist: marshmallow-utils<1.0.0,>=0.14.1
Requires-Dist: uritemplate>=3.0.1
Requires-Dist: wand<0.7.0,>=0.6.6
Requires-Dist: xmltodict~=0.12.0
Requires-Dist: zipstream-ng>=1.3.4
Provides-Extra: tests
Requires-Dist: pytest-black>=0.6.0; extra == "tests"
Requires-Dist: invenio-app<4.0.0,>=3.0.0; extra == "tests"
Requires-Dist: invenio-db[mysql,postgresql,versioning]<3.0.0,>=2.2.0; extra == "tests"
Requires-Dist: invenio-s3<5.0.0,>=4.0.0; extra == "tests"
Requires-Dist: pytest-invenio<5.0.0,>=4.0.0; extra == "tests"
Requires-Dist: pytest-mock>=1.6.0; extra == "tests"
Requires-Dist: sphinx<9,>=5; extra == "tests"
Provides-Extra: elasticsearch7
Requires-Dist: invenio-search[elasticsearch7]<4.0.0,>=3.0.0; extra == "elasticsearch7"
Provides-Extra: opensearch1
Requires-Dist: invenio-search[opensearch1]<4.0.0,>=3.0.0; extra == "opensearch1"
Provides-Extra: opensearch2
Requires-Dist: invenio-search[opensearch2]<4.0.0,>=3.0.0; extra == "opensearch2"
Dynamic: license-file
